tracy/__init__.py
tracy/__main__.py
tracy/style.qss
tracy/canvas_tools/__init__.py
tracy/canvas_tools/_shared.py
tracy/canvas_tools/animators.py
tracy/canvas_tools/controls.py
tracy/canvas_tools/dialogs.py
tracy/canvas_tools/layout.py
tracy/canvas_tools/recalc.py
tracy/canvas_tools/tooltips.py
tracy/canvas_tools/widgets.py
tracy/canvases/__init__.py
tracy/canvases/_shared.py
tracy/canvases/base.py
tracy/canvases/histogram.py
tracy/canvases/intensity.py
tracy/canvases/kymo.py
tracy/canvases/movie.py
tracy/canvases/trajectory.py
tracy/canvases/velocity.py
tracy/fonts/Figtree-Bold.ttf
tracy/fonts/Figtree-Regular.ttf
tracy/icons/contrast.svg
tracy/icons/cross-dot.svg
tracy/icons/cross-small.svg
tracy/icons/invert.svg
tracy/icons/log.svg
tracy/icons/max.svg
tracy/icons/overlay.svg
tracy/icons/overlay_anchor.svg
tracy/icons/overlay_one.svg
tracy/icons/overlay_traj.svg
tracy/icons/reference.svg
tracy/icons/tracybutton.svg
tracy/icons/tracyicon.png
tracy/navigator/__init__.py
tracy/navigator/_shared.py
tracy/navigator/analysis.py
tracy/navigator/colors.py
tracy/navigator/extra_calculations.py
tracy/navigator/input.py
tracy/navigator/io.py
tracy/navigator/kymo.py
tracy/navigator/main.py
tracy/navigator/movie.py
tracy/navigator/roi.py
tracy/navigator/ui.py
tracy/tools/__init__.py
tracy/tools/gaussian_tools.py
tracy/tools/roi_tools.py
tracy/tools/track_tools.py
tracyspot-1.3.10.dist-info/licenses/LICENSE
tracyspot-1.3.10.dist-info/METADATA
tracyspot-1.3.10.dist-info/WHEEL
tracyspot-1.3.10.dist-info/entry_points.txt
tracyspot-1.3.10.dist-info/top_level.txt
tracyspot-1.3.10.dist-info/RECORD
